[{"shop":"callhealth-coupons","title":"CallHealth Coupons and Offers","title_desc":" CallHealth is a healthcare ecosystem where access to good health is as easy as shopping online, that brings the healthca...See moreCallHealth is a healthcare ecosystem where access to good health is as easy as shopping online, that brings the healthcare provider, right at the doorstep, where you are never out of medicines and basic medical supplies. See less","category":"Beauty & Health","sub_category":"Medicines & Health Check-Ups","img":"https://d3pzq99hz695o4.cloudfront.net/sitespecific/in/stores/web/f4f09a374ea44d15970b1b07585a6f3f/callhealth-coupons-logo-large.png?469657 ","offer_title":"50% OFF","offer_desc":"Upto 50% Off + Extra 15% Off on Key Healthcare Services via ICICI Cards ","offer_code":"ICICI15"}]
