[{"shop":"droom","title":"droom Coupons and Offers","title_desc":" droom is India's first mobile marketplace to buy and sell new and used automobiles. ","category":"Automotive","sub_category":"Car Electronics","img":"https://d3pzq99hz695o4.cloudfront.net/sitespecific/in/stores/web/4c507c01e4de605a71a483fc3682e0ba/droom-logo-large.jpg?27077 ","offer_title":"Rs.25000 OFF","offer_desc":"Rs. 25,000 Off on Rs. 350,000 (Hyundai i10) ","offer_code":"CDDroomHi1072"},{"shop":"droom","title":"droom Coupons and Offers","title_desc":" droom is India's first mobile marketplace to buy and sell new and used automobiles. ","category":"Automotive","sub_category":"Car Electronics","img":"https://d3pzq99hz695o4.cloudfront.net/sitespecific/in/stores/web/4c507c01e4de605a71a483fc3682e0ba/droom-logo-large.jpg?27077 ","offer_title":"Rs.3000 OFF","offer_desc":"Rs. 3000 Off on Rs. 41,000 (Honda Aviator) ","offer_code":"CDDroomHAV26"}]
