[{"shop":"travelyaari","title":"Travelyaari Coupons","title_desc":" Travelyaari is a provider of bus tickets in India. It features bus tour operators such as Eagle Travels, KPN Travels, Ne...See moreTravelyaari is a provider of bus tickets in India. It features bus tour operators such as Eagle Travels, KPN Travels, Neeta Travels, Volvo, SETC, and many more. Some of the top Indian cities covered are Pune, Delhi, Ahmedabad, Bengaluru, Indore, Jaipur, Nagpur, Mumbai, Hyderabad, Chennai, Surat, Udaipur, Rajasthan, Aurangabad, Maharashtra, Jodhpur, Chandigarh, Kolhapur, Latur, Vadodara, Jalandhar, Kanpur See less","category":"Travel","sub_category":"Bus","img":"https://d3pzq99hz695o4.cloudfront.net/sitespecific/in/stores/web/d76d8c70441de7304c5dca5fad666f21/travelyaari-logo-large.jpg?385285 ","offer_title":"5% OFF","offer_desc":"Flat 5% Off on Your First Booking ","offer_code":"WEBYAARI"}]
