[{"shop":"yourdesignerwear","title":"Your Designer Wear Coupons 2nd January 2023","title_desc":" YourDesignerWear is an online shopping store exclusively selling a wide range of Sarees, designer sarees, designer salwa...See moreYourDesignerWear is an online shopping store exclusively selling a wide range of Sarees, designer sarees, designer salwar kameez, lehenga choli, kurtis, Tunics & Indian Jewelry. See less","category":"Fashion","sub_category":"Clothing","img":"https://d3pzq99hz695o4.cloudfront.net/sitespecific/in/stores/web/9311bff3413c0ae8a15e356cf5604af7/yourdesignerwear-logo-large.jpg?470689 ","offer_title":"20% OFF","offer_desc":"Flat 20% Off Sitewide ","offer_code":"WOMEN20"}]
